{
    "Default Profile": {
        "thermocoupleConfig": [
            {
                "channel": 1,
                "placement": {
                    "__enum__": "thermocouplePlacements.FURNACE"
                },
                "gain": 1.0,
                "offset": 0.0,
                "label": "FURNACE TC 1"
            },
            {
                "channel": 2,
                "placement": {
                    "__enum__": "thermocouplePlacements.FURNACE"
                },
                "gain": 1.0,
                "offset": 0.0,
                "label": "FURNACE TC 2"
            },
            {
                "channel": 3,
                "placement": {
                    "__enum__": "thermocouplePlacements.FURNACE"
                },
                "gain": 1.0,
                "offset": 0.0,
                "label": "FURNACE TC 3"
            },
            {
                "channel": 4,
                "placement": {
                    "__enum__": "thermocouplePlacements.FURNACE"
                },
                "gain": 1.0,
                "offset": 0.0,
                "label": "FURNACE TC 4"
            },
            {
                "channel": 5,
                "placement": {
                    "__enum__": "thermocouplePlacements.FURNACE"
                },
                "gain": 1.0,
                "offset": 0.0,
                "label": "FURNACE TC 5"
            },
            {
                "channel": 6,
                "placement": {
                    "__enum__": "thermocouplePlacements.FURNACE"
                },
                "gain": 1.0,
                "offset": 0.0,
                "label": "FURNACE TC 6"
            },
            {
                "channel": 7,
                "placement": {
                    "__enum__": "thermocouplePlacements.FURNACE"
                },
                "gain": 1.0,
                "offset": 0.0,
                "label": "FURNACE TC 7"
            },
            {
                "channel": 8,
                "placement": {
                    "__enum__": "thermocouplePlacements.FURNACE"
                },
                "gain": 1.0,
                "offset": 0.0,
                "label": "FURNACE TC 8"
            },
            {
                "channel": 9,
                "placement": {
                    "__enum__": "thermocouplePlacements.FURNACE"
                },
                "gain": 1.0,
                "offset": 0.0,
                "label": "FURNACE TC 9"
            },
            {
                "channel": 10,
                "placement": {
                    "__enum__": "thermocouplePlacements.FURNACE"
                },
                "gain": 1.0,
                "offset": 0.0,
                "label": "FURNACE TC 10"
            },
            {
                "channel": 11,
                "placement": {
                    "__enum__": "thermocouplePlacements.FURNACE"
                },
                "gain": 1.0,
                "offset": 0.0,
                "label": "FURNACE TC 11"
            },
            {
                "channel": 12,
                "placement": {
                    "__enum__": "thermocouplePlacements.FURNACE"
                },
                "gain": 1.0,
                "offset": 0.0,
                "label": "FURNACE TC 12"
            },
            {
                "channel": 13,
                "placement": {
                    "__enum__": "thermocouplePlacements.AFTERBURNER"
                },
                "gain": 1.0,
                "offset": 0.0,
                "label": "UPPER AFTERBURNER TC"
            },
            {
                "channel": 14,
                "placement": {
                    "__enum__": "thermocouplePlacements.AFTERBURNER"
                },
                "gain": 1.0,
                "offset": 0.0,
                "label": "LOWER AFTERBURNER TC"
            },
            {
                "channel": 15,
                "placement": {
                    "__enum__": "thermocouplePlacements.DISABLED"
                },
                "gain": 1.0,
                "offset": 0.0,
                "label": "SPARE TC"
            },
            {
                "channel": 16,
                "placement": {
                    "__enum__": "thermocouplePlacements.DISABLED"
                },
                "gain": 1.0,
                "offset": 0.0,
                "label": "SPARE TC"
            },
            {
                "channel": 17,
                "placement": {
                    "__enum__": "thermocouplePlacements.UNEXPOSED"
                },
                "gain": 1.0,
                "offset": 0.0,
                "label": "UNEXPOSED TC "
            },
            {
                "channel": 18,
                "placement": {
                    "__enum__": "thermocouplePlacements.UNEXPOSED"
                },
                "gain": 1.0,
                "offset": 0.0,
                "label": "UNEXPOSED TC "
            },
            {
                "channel": 19,
                "placement": {
                    "__enum__": "thermocouplePlacements.UNEXPOSED"
                },
                "gain": 1.0,
                "offset": 0.0,
                "label": "UNEXPOSED TC "
            },
            {
                "channel": 20,
                "placement": {
                    "__enum__": "thermocouplePlacements.UNEXPOSED"
                },
                "gain": 1.0,
                "offset": 0.0,
                "label": "UNEXPOSED TC "
            },
            {
                "channel": 21,
                "placement": {
                    "__enum__": "thermocouplePlacements.UNEXPOSED"
                },
                "gain": 1.0,
                "offset": 0.0,
                "label": "UNEXPOSED TC "
            },
            {
                "channel": 22,
                "placement": {
                    "__enum__": "thermocouplePlacements.UNEXPOSED"
                },
                "gain": 1.0,
                "offset": 0.0,
                "label": "UNEXPOSED TC "
            },
            {
                "channel": 23,
                "placement": {
                    "__enum__": "thermocouplePlacements.UNEXPOSED"
                },
                "gain": 1.0,
                "offset": 0.0,
                "label": "UNEXPOSED TC "
            },
            {
                "channel": 24,
                "placement": {
                    "__enum__": "thermocouplePlacements.UNEXPOSED"
                },
                "gain": 1.0,
                "offset": 0.0,
                "label": "UNEXPOSED TC "
            },
            {
                "channel": 25,
                "placement": {
                    "__enum__": "thermocouplePlacements.UNEXPOSED"
                },
                "gain": 1.0,
                "offset": 0.0,
                "label": "UNEXPOSED TC "
            },
            {
                "channel": 26,
                "placement": {
                    "__enum__": "thermocouplePlacements.UNEXPOSED"
                },
                "gain": 1.0,
                "offset": 0.0,
                "label": "UNEXPOSED TC "
            },
            {
                "channel": 27,
                "placement": {
                    "__enum__": "thermocouplePlacements.UNEXPOSED"
                },
                "gain": 1.0,
                "offset": 0.0,
                "label": "UNEXPOSED TC "
            },
            {
                "channel": 28,
                "placement": {
                    "__enum__": "thermocouplePlacements.UNEXPOSED"
                },
                "gain": 1.0,
                "offset": 0.0,
                "label": "UNEXPOSED TC "
            },
            {
                "channel": 29,
                "placement": {
                    "__enum__": "thermocouplePlacements.UNEXPOSED"
                },
                "gain": 1.0,
                "offset": 0.0,
                "label": "UNEXPOSED TC "
            },
            {
                "channel": 30,
                "placement": {
                    "__enum__": "thermocouplePlacements.UNEXPOSED"
                },
                "gain": 1.0,
                "offset": 0.0,
                "label": "UNEXPOSED TC "
            },
            {
                "channel": 31,
                "placement": {
                    "__enum__": "thermocouplePlacements.UNEXPOSED"
                },
                "gain": 1.0,
                "offset": 0.0,
                "label": "UNEXPOSED TC "
            },
            {
                "channel": 32,
                "placement": {
                    "__enum__": "thermocouplePlacements.UNEXPOSED"
                },
                "gain": 1.0,
                "offset": 0.0,
                "label": "UNEXPOSED TC "
            },
            {
                "channel": 33,
                "placement": {
                    "__enum__": "thermocouplePlacements.UNEXPOSED"
                },
                "gain": 1.0,
                "offset": 0.0,
                "label": "UNEXPOSED TC "
            },
            {
                "channel": 34,
                "placement": {
                    "__enum__": "thermocouplePlacements.UNEXPOSED"
                },
                "gain": 1.0,
                "offset": 0.0,
                "label": "UNEXPOSED TC "
            },
            {
                "channel": 35,
                "placement": {
                    "__enum__": "thermocouplePlacements.UNEXPOSED"
                },
                "gain": 1.0,
                "offset": 0.0,
                "label": "UNEXPOSED TC "
            },
            {
                "channel": 36,
                "placement": {
                    "__enum__": "thermocouplePlacements.UNEXPOSED"
                },
                "gain": 1.0,
                "offset": 0.0,
                "label": "UNEXPOSED TC "
            },
            {
                "channel": 37,
                "placement": {
                    "__enum__": "thermocouplePlacements.UNEXPOSED"
                },
                "gain": 1.0,
                "offset": 0.0,
                "label": "UNEXPOSED TC "
            },
            {
                "channel": 38,
                "placement": {
                    "__enum__": "thermocouplePlacements.UNEXPOSED"
                },
                "gain": 1.0,
                "offset": 0.0,
                "label": "UNEXPOSED TC "
            },
            {
                "channel": 39,
                "placement": {
                    "__enum__": "thermocouplePlacements.UNEXPOSED"
                },
                "gain": 1.0,
                "offset": 0.0,
                "label": "UNEXPOSED TC "
            },
            {
                "channel": 40,
                "placement": {
                    "__enum__": "thermocouplePlacements.UNEXPOSED"
                },
                "gain": 1.0,
                "offset": 0.0,
                "label": "UNEXPOSED TC "
            },
            {
                "channel": 41,
                "placement": {
                    "__enum__": "thermocouplePlacements.UNEXPOSED"
                },
                "gain": 1.0,
                "offset": 0.0,
                "label": "UNEXPOSED TC "
            },
            {
                "channel": 42,
                "placement": {
                    "__enum__": "thermocouplePlacements.UNEXPOSED"
                },
                "gain": 1.0,
                "offset": 0.0,
                "label": "UNEXPOSED TC "
            },
            {
                "channel": 43,
                "placement": {
                    "__enum__": "thermocouplePlacements.UNEXPOSED"
                },
                "gain": 1.0,
                "offset": 0.0,
                "label": "UNEXPOSED TC "
            },
            {
                "channel": 44,
                "placement": {
                    "__enum__": "thermocouplePlacements.UNEXPOSED"
                },
                "gain": 1.0,
                "offset": 0.0,
                "label": "UNEXPOSED TC "
            },
            {
                "channel": 45,
                "placement": {
                    "__enum__": "thermocouplePlacements.UNEXPOSED"
                },
                "gain": 1.0,
                "offset": 0.0,
                "label": "UNEXPOSED TC "
            },
            {
                "channel": 46,
                "placement": {
                    "__enum__": "thermocouplePlacements.UNEXPOSED"
                },
                "gain": 1.0,
                "offset": 0.0,
                "label": "UNEXPOSED TC "
            },
            {
                "channel": 47,
                "placement": {
                    "__enum__": "thermocouplePlacements.UNEXPOSED"
                },
                "gain": 1.0,
                "offset": 0.0,
                "label": "UNEXPOSED TC "
            },
            {
                "channel": 48,
                "placement": {
                    "__enum__": "thermocouplePlacements.UNEXPOSED"
                },
                "gain": 1.0,
                "offset": 0.0,
                "label": "UNEXPOSED TC "
            },
            {
                "channel": 49,
                "placement": {
                    "__enum__": "thermocouplePlacements.UNEXPOSED"
                },
                "gain": 1.0,
                "offset": 0.0,
                "label": "UNEXPOSED TC "
            },
            {
                "channel": 50,
                "placement": {
                    "__enum__": "thermocouplePlacements.UNEXPOSED"
                },
                "gain": 1.0,
                "offset": 0.0,
                "label": "UNEXPOSED TC "
            },
            {
                "channel": 51,
                "placement": {
                    "__enum__": "thermocouplePlacements.UNEXPOSED"
                },
                "gain": 1.0,
                "offset": 0.0,
                "label": "UNEXPOSED TC "
            },
            {
                "channel": 52,
                "placement": {
                    "__enum__": "thermocouplePlacements.UNEXPOSED"
                },
                "gain": 1.0,
                "offset": 0.0,
                "label": "UNEXPOSED TC "
            },
            {
                "channel": 53,
                "placement": {
                    "__enum__": "thermocouplePlacements.UNEXPOSED"
                },
                "gain": 1.0,
                "offset": 0.0,
                "label": "UNEXPOSED TC "
            },
            {
                "channel": 54,
                "placement": {
                    "__enum__": "thermocouplePlacements.UNEXPOSED"
                },
                "gain": 1.0,
                "offset": 0.0,
                "label": "UNEXPOSED TC "
            },
            {
                "channel": 55,
                "placement": {
                    "__enum__": "thermocouplePlacements.UNEXPOSED"
                },
                "gain": 1.0,
                "offset": 0.0,
                "label": "UNEXPOSED TC "
            },
            {
                "channel": 56,
                "placement": {
                    "__enum__": "thermocouplePlacements.UNEXPOSED"
                },
                "gain": 1.0,
                "offset": 0.0,
                "label": "UNEXPOSED TC "
            },
            {
                "channel": 57,
                "placement": {
                    "__enum__": "thermocouplePlacements.UNEXPOSED"
                },
                "gain": 1.0,
                "offset": 0.0,
                "label": "UNEXPOSED TC "
            },
            {
                "channel": 58,
                "placement": {
                    "__enum__": "thermocouplePlacements.UNEXPOSED"
                },
                "gain": 1.0,
                "offset": 0.0,
                "label": "UNEXPOSED TC "
            },
            {
                "channel": 59,
                "placement": {
                    "__enum__": "thermocouplePlacements.UNEXPOSED"
                },
                "gain": 1.0,
                "offset": 0.0,
                "label": "UNEXPOSED TC "
            },
            {
                "channel": 60,
                "placement": {
                    "__enum__": "thermocouplePlacements.UNEXPOSED"
                },
                "gain": 1.0,
                "offset": 0.0,
                "label": "UNEXPOSED TC "
            },
            {
                "channel": 61,
                "placement": {
                    "__enum__": "thermocouplePlacements.UNEXPOSED"
                },
                "gain": 1.0,
                "offset": 0.0,
                "label": "UNEXPOSED TC "
            },
            {
                "channel": 62,
                "placement": {
                    "__enum__": "thermocouplePlacements.UNEXPOSED"
                },
                "gain": 1.0,
                "offset": 0.0,
                "label": "UNEXPOSED TC "
            },
            {
                "channel": 63,
                "placement": {
                    "__enum__": "thermocouplePlacements.UNEXPOSED"
                },
                "gain": 1.0,
                "offset": 0.0,
                "label": "UNEXPOSED TC "
            },
            {
                "channel": 64,
                "placement": {
                    "__enum__": "thermocouplePlacements.UNEXPOSED"
                },
                "gain": 1.0,
                "offset": 0.0,
                "label": "UNEXPOSED TC "
            },
            {
                "channel": 21,
                "placement": {
                    "__enum__": "thermocouplePlacements.DISABLED"
                },
                "gain": 1.0,
                "offset": 0.0,
                "label": "Channel 21"
            },
            {
                "channel": 22,
                "placement": {
                    "__enum__": "thermocouplePlacements.DISABLED"
                },
                "gain": 1.0,
                "offset": 0.0,
                "label": "Channel 22"
            },
            {
                "channel": 23,
                "placement": {
                    "__enum__": "thermocouplePlacements.DISABLED"
                },
                "gain": 1.0,
                "offset": 0.0,
                "label": "Channel 23"
            },
            {
                "channel": 24,
                "placement": {
                    "__enum__": "thermocouplePlacements.DISABLED"
                },
                "gain": 1.0,
                "offset": 0.0,
                "label": "Channel 24"
            },
            {
                "channel": 25,
                "placement": {
                    "__enum__": "thermocouplePlacements.DISABLED"
                },
                "gain": 1.0,
                "offset": 0.0,
                "label": "Channel 25"
            },
            {
                "channel": 26,
                "placement": {
                    "__enum__": "thermocouplePlacements.DISABLED"
                },
                "gain": 1.0,
                "offset": 0.0,
                "label": "Channel 26"
            },
            {
                "channel": 27,
                "placement": {
                    "__enum__": "thermocouplePlacements.DISABLED"
                },
                "gain": 1.0,
                "offset": 0.0,
                "label": "Channel 27"
            },
            {
                "channel": 28,
                "placement": {
                    "__enum__": "thermocouplePlacements.DISABLED"
                },
                "gain": 1.0,
                "offset": 0.0,
                "label": "Channel 28"
            },
            {
                "channel": 29,
                "placement": {
                    "__enum__": "thermocouplePlacements.DISABLED"
                },
                "gain": 1.0,
                "offset": 0.0,
                "label": "Channel 29"
            },
            {
                "channel": 30,
                "placement": {
                    "__enum__": "thermocouplePlacements.DISABLED"
                },
                "gain": 1.0,
                "offset": 0.0,
                "label": "Channel 30"
            },
            {
                "channel": 31,
                "placement": {
                    "__enum__": "thermocouplePlacements.DISABLED"
                },
                "gain": 1.0,
                "offset": 0.0,
                "label": "Channel 31"
            },
            {
                "channel": 32,
                "placement": {
                    "__enum__": "thermocouplePlacements.DISABLED"
                },
                "gain": 1.0,
                "offset": 0.0,
                "label": "Channel 32"
            },
            {
                "channel": 33,
                "placement": {
                    "__enum__": "thermocouplePlacements.DISABLED"
                },
                "gain": 1.0,
                "offset": 0.0,
                "label": "Channel 33"
            },
            {
                "channel": 34,
                "placement": {
                    "__enum__": "thermocouplePlacements.DISABLED"
                },
                "gain": 1.0,
                "offset": 0.0,
                "label": "Channel 34"
            },
            {
                "channel": 35,
                "placement": {
                    "__enum__": "thermocouplePlacements.DISABLED"
                },
                "gain": 1.0,
                "offset": 0.0,
                "label": "Channel 35"
            },
            {
                "channel": 36,
                "placement": {
                    "__enum__": "thermocouplePlacements.DISABLED"
                },
                "gain": 1.0,
                "offset": 0.0,
                "label": "Channel 36"
            },
            {
                "channel": 37,
                "placement": {
                    "__enum__": "thermocouplePlacements.DISABLED"
                },
                "gain": 1.0,
                "offset": 0.0,
                "label": "Channel 37"
            },
            {
                "channel": 38,
                "placement": {
                    "__enum__": "thermocouplePlacements.DISABLED"
                },
                "gain": 1.0,
                "offset": 0.0,
                "label": "Channel 38"
            },
            {
                "channel": 39,
                "placement": {
                    "__enum__": "thermocouplePlacements.DISABLED"
                },
                "gain": 1.0,
                "offset": 0.0,
                "label": "Channel 39"
            },
            {
                "channel": 40,
                "placement": {
                    "__enum__": "thermocouplePlacements.DISABLED"
                },
                "gain": 1.0,
                "offset": 0.0,
                "label": "Channel 40"
            },
            {
                "channel": 41,
                "placement": {
                    "__enum__": "thermocouplePlacements.DISABLED"
                },
                "gain": 1.0,
                "offset": 0.0,
                "label": "Channel 41"
            },
            {
                "channel": 42,
                "placement": {
                    "__enum__": "thermocouplePlacements.DISABLED"
                },
                "gain": 1.0,
                "offset": 0.0,
                "label": "Channel 42"
            },
            {
                "channel": 43,
                "placement": {
                    "__enum__": "thermocouplePlacements.DISABLED"
                },
                "gain": 1.0,
                "offset": 0.0,
                "label": "Channel 43"
            },
            {
                "channel": 44,
                "placement": {
                    "__enum__": "thermocouplePlacements.DISABLED"
                },
                "gain": 1.0,
                "offset": 0.0,
                "label": "Channel 44"
            },
            {
                "channel": 45,
                "placement": {
                    "__enum__": "thermocouplePlacements.DISABLED"
                },
                "gain": 1.0,
                "offset": 0.0,
                "label": "Channel 45"
            },
            {
                "channel": 46,
                "placement": {
                    "__enum__": "thermocouplePlacements.DISABLED"
                },
                "gain": 1.0,
                "offset": 0.0,
                "label": "Channel 46"
            },
            {
                "channel": 47,
                "placement": {
                    "__enum__": "thermocouplePlacements.DISABLED"
                },
                "gain": 1.0,
                "offset": 0.0,
                "label": "Channel 47"
            },
            {
                "channel": 48,
                "placement": {
                    "__enum__": "thermocouplePlacements.DISABLED"
                },
                "gain": 1.0,
                "offset": 0.0,
                "label": "Channel 48"
            },
            {
                "channel": 49,
                "placement": {
                    "__enum__": "thermocouplePlacements.DISABLED"
                },
                "gain": 1.0,
                "offset": 0.0,
                "label": "Channel 49"
            },
            {
                "channel": 50,
                "placement": {
                    "__enum__": "thermocouplePlacements.DISABLED"
                },
                "gain": 1.0,
                "offset": 0.0,
                "label": "Channel 50"
            },
            {
                "channel": 51,
                "placement": {
                    "__enum__": "thermocouplePlacements.DISABLED"
                },
                "gain": 1.0,
                "offset": 0.0,
                "label": "Channel 51"
            },
            {
                "channel": 52,
                "placement": {
                    "__enum__": "thermocouplePlacements.DISABLED"
                },
                "gain": 1.0,
                "offset": 0.0,
                "label": "Channel 52"
            },
            {
                "channel": 53,
                "placement": {
                    "__enum__": "thermocouplePlacements.DISABLED"
                },
                "gain": 1.0,
                "offset": 0.0,
                "label": "Channel 53"
            },
            {
                "channel": 54,
                "placement": {
                    "__enum__": "thermocouplePlacements.DISABLED"
                },
                "gain": 1.0,
                "offset": 0.0,
                "label": "Channel 54"
            },
            {
                "channel": 55,
                "placement": {
                    "__enum__": "thermocouplePlacements.DISABLED"
                },
                "gain": 1.0,
                "offset": 0.0,
                "label": "Channel 55"
            },
            {
                "channel": 56,
                "placement": {
                    "__enum__": "thermocouplePlacements.DISABLED"
                },
                "gain": 1.0,
                "offset": 0.0,
                "label": "Channel 56"
            },
            {
                "channel": 57,
                "placement": {
                    "__enum__": "thermocouplePlacements.DISABLED"
                },
                "gain": 1.0,
                "offset": 0.0,
                "label": "Channel 57"
            },
            {
                "channel": 58,
                "placement": {
                    "__enum__": "thermocouplePlacements.DISABLED"
                },
                "gain": 1.0,
                "offset": 0.0,
                "label": "Channel 58"
            },
            {
                "channel": 59,
                "placement": {
                    "__enum__": "thermocouplePlacements.DISABLED"
                },
                "gain": 1.0,
                "offset": 0.0,
                "label": "Channel 59"
            },
            {
                "channel": 60,
                "placement": {
                    "__enum__": "thermocouplePlacements.DISABLED"
                },
                "gain": 1.0,
                "offset": 0.0,
                "label": "Channel 60"
            }
        ],
        "pressureConfig": [
            {
                "DISABLED": {
                    "gain": 1.0,
                    "offset": 0.0
                }
            },
            {
                "DISABLED": {
                    "gain": 1.0,
                    "offset": 0.0
                }
            },
            {
                "DISABLED": {
                    "gain": 1.0,
                    "offset": 0.0
                }
            }
        ],
        "currentPressuresSerial": [
            "DISABLED",
            "DISABLED",
            "DISABLED"
        ],
        "unexposedFailureThreshold": 180.0,
        "afterburnerThreshold": [
            1600.0,
            1600.0
        ]
    }
}